README.rst
setup.py
Operation/__init__.py
Operation/operations.py
hourflow.egg-info/PKG-INFO
hourflow.egg-info/SOURCES.txt
hourflow.egg-info/dependency_links.txt
hourflow.egg-info/top_level.txt